gluepy_mlflow/__init__.py
gluepy_mlflow/backend.py
gluepy_mlflow/commands.py
gluepy_mlflow-0.3.1.dist-info/LICENSE
gluepy_mlflow-0.3.1.dist-info/METADATA
gluepy_mlflow-0.3.1.dist-info/WHEEL
gluepy_mlflow-0.3.1.dist-info/top_level.txt
gluepy_mlflow-0.3.1.dist-info/RECORD
